gait_40_dof_22_musc_sagittal/MUJOCO_LOG.TXT
gait_40_dof_22_musc_sagittal/__init__.py
gait_40_dof_22_musc_sagittal/model/2d.xml
gait_40_dof_22_musc_sagittal/model/Converted/floor0.png
gait_40_dof_22_musc_sagittal/model/Converted/hat_jaw.stl
gait_40_dof_22_musc_sagittal/model/Converted/hat_ribs.stl
gait_40_dof_22_musc_sagittal/model/Converted/hat_skull.stl
gait_40_dof_22_musc_sagittal/model/Converted/hat_spine.stl
gait_40_dof_22_musc_sagittal/model/Converted/l_bofoot.stl
gait_40_dof_22_musc_sagittal/model/Converted/l_femur.stl
gait_40_dof_22_musc_sagittal/model/Converted/l_fibula.stl
gait_40_dof_22_musc_sagittal/model/Converted/l_foot.stl
gait_40_dof_22_musc_sagittal/model/Converted/l_pelvis.stl
gait_40_dof_22_musc_sagittal/model/Converted/l_talus.stl
gait_40_dof_22_musc_sagittal/model/Converted/l_tibia.stl
gait_40_dof_22_musc_sagittal/model/Converted/r_bofoot.stl
gait_40_dof_22_musc_sagittal/model/Converted/r_femur.stl
gait_40_dof_22_musc_sagittal/model/Converted/r_fibula.stl
gait_40_dof_22_musc_sagittal/model/Converted/r_foot.stl
gait_40_dof_22_musc_sagittal/model/Converted/r_pelvis.stl
gait_40_dof_22_musc_sagittal/model/Converted/r_talus.stl
gait_40_dof_22_musc_sagittal/model/Converted/r_tibia.stl
gait_40_dof_22_musc_sagittal/model/Converted/sacrum.stl
gait_40_dof_22_musc_sagittal/sagittal_walking_env.py
gait_40_dof_22_musc_sagittal-0.1.4.dist-info/METADATA
gait_40_dof_22_musc_sagittal-0.1.4.dist-info/WHEEL
gait_40_dof_22_musc_sagittal-0.1.4.dist-info/RECORD
